greenformatics_ds2_utils/__init__.py
greenformatics_ds2_utils/connector/__init__.py
greenformatics_ds2_utils/connector/database/__init__.py
greenformatics_ds2_utils/connector/database/base.py
greenformatics_ds2_utils/connector/google/__init__.py
greenformatics_ds2_utils/connector/google/sheets/__init__.py
greenformatics_ds2_utils/connector/google/sheets/repository.py
greenformatics_ds2_utils/converter/__init__.py
greenformatics_ds2_utils/logger/__init__.py
greenformatics_ds2_utils/logger/database_connection.py
greenformatics_ds2_utils/logger/database_handler.py
greenformatics_ds2_utils/logger/loading_log.py
greenformatics_ds2_utils/logger/loading_log_repository.py
greenformatics_ds2_utils/mapper/__init__.py
greenformatics_ds2_utils/parser/__init__.py
greenformatics_ds2_utils/validator/__init__.py
greenformatics_ds2_utils/validator/slugvalidator.py
tests/__init__.py
tests/test_converter.py
tests/test_logger.py
tests/test_mapper.py
tests/test_util.py
greenformatics_ds2_utils-1.2.16.dist-info/METADATA
greenformatics_ds2_utils-1.2.16.dist-info/WHEEL
greenformatics_ds2_utils-1.2.16.dist-info/top_level.txt
greenformatics_ds2_utils-1.2.16.dist-info/RECORD
