Metadata-Version: 2.1
Name: greenformatics-ds2-utils
Version: 1.2.16
Summary: This is a utility package to support data scraping from different data sources.
Author: Adam Fónagy
Keywords: python,data scraping,utilities,util,utility
Classifier: Programming Language :: Python :: 3
Classifier: Operating System :: OS Independent
Classifier: License :: OSI Approved :: MIT License
Requires-Python: >=3.6
Requires-Dist: psycopg2 >=2.9.5
Requires-Dist: mock >=4.0.3
Requires-Dist: sqlalchemy >=1.4.42
Requires-Dist: requests >=2.28.1
Requires-Dist: google-api-python-client >=2.76.0
Requires-Dist: google-auth-httplib2 >=0.1.0
